st_image_button/__init__.py
st_image_button/example.py
st_image_button/frontend/build/asset-manifest.json
st_image_button/frontend/build/bootstrap.min.css
st_image_button/frontend/build/index.html
st_image_button/frontend/build/static/js/main.17794c2c.js
st_image_button/frontend/build/static/js/main.17794c2c.js.LICENSE.txt
st_image_button/frontend/build/static/js/main.17794c2c.js.map
st_image_button/frontend/build/static/js/main.1bd8e4e7.js
st_image_button/frontend/build/static/js/main.1bd8e4e7.js.LICENSE.txt
st_image_button/frontend/build/static/js/main.1bd8e4e7.js.map
st_image_button/frontend/build/static/js/main.248e6620.js
st_image_button/frontend/build/static/js/main.248e6620.js.LICENSE.txt
st_image_button/frontend/build/static/js/main.248e6620.js.map
st_image_button/frontend/build/static/js/main.2c8c2dc7.js
st_image_button/frontend/build/static/js/main.2c8c2dc7.js.LICENSE.txt
st_image_button/frontend/build/static/js/main.2c8c2dc7.js.map
st_image_button/frontend/build/static/js/main.2fd8e011.js
st_image_button/frontend/build/static/js/main.2fd8e011.js.LICENSE.txt
st_image_button/frontend/build/static/js/main.2fd8e011.js.map
st_image_button/frontend/build/static/js/main.313699bf.js
st_image_button/frontend/build/static/js/main.313699bf.js.LICENSE.txt
st_image_button/frontend/build/static/js/main.313699bf.js.map
st_image_button/frontend/build/static/js/main.408f0e7a.js
st_image_button/frontend/build/static/js/main.408f0e7a.js.LICENSE.txt
st_image_button/frontend/build/static/js/main.408f0e7a.js.map
st_image_button/frontend/build/static/js/main.48b3061d.js
st_image_button/frontend/build/static/js/main.48b3061d.js.LICENSE.txt
st_image_button/frontend/build/static/js/main.48b3061d.js.map
st_image_button/frontend/build/static/js/main.5711d955.js
st_image_button/frontend/build/static/js/main.5711d955.js.LICENSE.txt
st_image_button/frontend/build/static/js/main.5711d955.js.map
st_image_button/frontend/build/static/js/main.58e5b5c3.js
streamlit_image_button-0.2.2.13.dist-info/LICENSE
streamlit_image_button-0.2.2.13.dist-info/METADATA
streamlit_image_button-0.2.2.13.dist-info/WHEEL
streamlit_image_button-0.2.2.13.dist-info/top_level.txt
streamlit_image_button-0.2.2.13.dist-info/RECORD
