Metadata-Version: 2.1
Name: streamlit-image-button
Version: 0.2.2.13
Summary: Streamlit component that allows you to create image buttons.
Home-page: 
Author: Anthony Pecquenard
Author-email: anthony.pecquenard@ens-lyon.fr
Requires-Python: >=3.7
License-File: LICENSE
Requires-Dist: streamlit>=0.63
Provides-Extra: devel
Requires-Dist: wheel; extra == "devel"
Requires-Dist: pytest==7.4.0; extra == "devel"
Requires-Dist: playwright==1.39.0; extra == "devel"
Requires-Dist: requests==2.31.0; extra == "devel"
Requires-Dist: pytest-playwright-snapshot==1.0; extra == "devel"
Requires-Dist: pytest-rerunfailures==12.0; extra == "devel"
